imagecolorclassifier/__init__.py
imagecolorclassifier/main.py
imagecolorclassifier-0.1.dist-info/METADATA
imagecolorclassifier-0.1.dist-info/WHEEL
imagecolorclassifier-0.1.dist-info/top_level.txt
imagecolorclassifier-0.1.dist-info/RECORD
