Metadata-Version: 2.1
Name: imagecolorclassifier
Version: 0.1
Requires-Dist: opencv-python-headless>=4.5.0
Requires-Dist: numpy>=1.19.0
